{
  "symbol": "ARKG",
  "holdings": [
    {
      "symbol": "TEM",
      "weight": 0.0944802,
      "daily": 1.33
    },
    {
      "symbol": "TWST",
      "weight": 0.090150006,
      "daily": 9.65
    },
    {
      "symbol": "CRSP",
      "weight": 0.089356005,
      "daily": 2.78
    },
    {
      "symbol": "TXG",
      "weight": 0.0578439,
      "daily": 2.92
    },
    {
      "symbol": "BEAM",
      "weight": 0.0544493,
      "daily": 2.07
    },
    {
      "symbol": "ABSI",
      "weight": 0.0479485,
      "daily": 2.83
    },
    {
      "symbol": "NTRA",
      "weight": 0.0407753,
      "daily": -0.6
    },
    {
      "symbol": "ILMN",
      "weight": 0.0404044,
      "daily": 2.05
    },
    {
      "symbol": "NTLA",
      "weight": 0.0382705,
      "daily": 0.9
    },
    {
      "symbol": "PSNL",
      "weight": 0.0359144,
      "daily": 3.77
    }
  ]
}