{
  "symbol": "DIA",
  "holdings": [
    {
      "symbol": "GS",
      "weight": 0.1121074,
      "daily": -0.47
    },
    {
      "symbol": "CAT",
      "weight": 0.0938825,
      "daily": -0.53
    },
    {
      "symbol": "MSFT",
      "weight": 0.0490535,
      "daily": 2.13
    },
    {
      "symbol": "AMGN",
      "weight": 0.0466258,
      "daily": -1.17
    },
    {
      "symbol": "HD",
      "weight": 0.043583296,
      "daily": -1.26
    },
    {
      "symbol": "SHW",
      "weight": 0.0424781,
      "daily": 0.01
    },
    {
      "symbol": "MCD",
      "weight": 0.0411847,
      "daily": -1.05
    },
    {
      "symbol": "AXP",
      "weight": 0.040083498,
      "daily": -1.4
    },
    {
      "symbol": "V",
      "weight": 0.0400517,
      "daily": 0.17
    },
    {
      "symbol": "JPM",
      "weight": 0.038980998,
      "daily": -1.09
    }
  ]
}