{
  "symbol": "EWI",
  "holdings": [
    {
      "symbol": "UCG.MI",
      "weight": 0.1478776,
      "daily": -0.2
    },
    {
      "symbol": "ENEL.MI",
      "weight": 0.1314271,
      "daily": 0.29
    },
    {
      "symbol": "ISP.MI",
      "weight": 0.1240742,
      "daily": 0.26
    },
    {
      "symbol": "ENI.MI",
      "weight": 0.0638176,
      "daily": -0.58
    },
    {
      "symbol": "PRY.MI",
      "weight": 0.0465874,
      "daily": 0.25
    },
    {
      "symbol": "LDO.MI",
      "weight": 0.045736,
      "daily": -0.05
    },
    {
      "symbol": "G.MI",
      "weight": 0.0450231,
      "daily": 0.57
    },
    {
      "symbol": "RACE.MI",
      "weight": 0.0422646,
      "daily": 0.5
    },
    {
      "symbol": "BPE.MI",
      "weight": 0.0328523,
      "daily": 0.4
    },
    {
      "symbol": "TRN.MI",
      "weight": 0.028546501,
      "daily": 0.0
    }
  ]
}