{
  "symbol": "EWL",
  "holdings": [
    {
      "symbol": "ROG",
      "weight": 0.1512936,
      "daily": 2.04
    },
    {
      "symbol": "NOVN.SW",
      "weight": 0.145402,
      "daily": 1.17
    },
    {
      "symbol": "NESN.SW",
      "weight": 0.1262842,
      "daily": 2.18
    },
    {
      "symbol": "ZURN.SW",
      "weight": 0.0449184,
      "daily": 0.86
    },
    {
      "symbol": "ABBN.SW",
      "weight": 0.044896998,
      "daily": 1.02
    },
    {
      "symbol": "CFR.SW",
      "weight": 0.043235604,
      "daily": 0.58
    },
    {
      "symbol": "UBSG.SW",
      "weight": 0.0429632,
      "daily": -0.37
    },
    {
      "symbol": "SREN.SW",
      "weight": 0.026043799,
      "daily": 0.51
    },
    {
      "symbol": "LONN.SW",
      "weight": 0.0244315,
      "daily": 1.99
    },
    {
      "symbol": "HOLN.SW",
      "weight": 0.0234918,
      "daily": 1.83
    }
  ]
}