{
  "symbol": "EWS",
  "holdings": [
    {
      "symbol": "D05.SI",
      "weight": 0.2237678,
      "daily": 3.43
    },
    {
      "symbol": "O39.SI",
      "weight": 0.1966244,
      "daily": 1.11
    },
    {
      "symbol": "BS6.SI",
      "weight": 0.0491429,
      "daily": -0.46
    },
    {
      "symbol": "F34.SI",
      "weight": 0.0490728,
      "daily": -5.74
    },
    {
      "symbol": "S68.SI",
      "weight": 0.0489592,
      "daily": 1.93
    },
    {
      "symbol": "S63.SI",
      "weight": 0.0484779,
      "daily": 0.66
    },
    {
      "symbol": "U96.SI",
      "weight": 0.0474898,
      "daily": 0.15
    },
    {
      "symbol": "Z74.SI",
      "weight": 0.0460452,
      "daily": 1.32
    },
    {
      "symbol": "U11.SI",
      "weight": 0.0427156,
      "daily": 1.03
    },
    {
      "symbol": "C6L.SI",
      "weight": 0.0424962,
      "daily": -0.32
    }
  ]
}