{
  "symbol": "IBUY",
  "holdings": [
    {
      "symbol": "FIGS",
      "weight": 0.0537733,
      "daily": -2.04
    },
    {
      "symbol": "LQDT",
      "weight": 0.0355322,
      "daily": 0.98
    },
    {
      "symbol": "RVLV",
      "weight": 0.0299267,
      "daily": 0.32
    },
    {
      "symbol": "EBAY",
      "weight": 0.029590098,
      "daily": 0.03
    },
    {
      "symbol": "ABNB",
      "weight": 0.029098202,
      "daily": 0.19
    },
    {
      "symbol": "MSM",
      "weight": 0.0285624,
      "daily": -0.37
    },
    {
      "symbol": "CVNA",
      "weight": 0.028469501,
      "daily": -3.72
    },
    {
      "symbol": "CART",
      "weight": 0.0271942,
      "daily": 4.12
    },
    {
      "symbol": "EXPE",
      "weight": 0.026614899,
      "daily": 0.31
    },
    {
      "symbol": "ETSY",
      "weight": 0.024019402,
      "daily": 0.4
    }
  ]
}