{
  "symbol": "IJK",
  "holdings": [
    {
      "symbol": "FLEX",
      "weight": 0.019341,
      "daily": 39.69
    },
    {
      "symbol": "FTI",
      "weight": 0.0175649,
      "daily": -1.45
    },
    {
      "symbol": "CW",
      "weight": 0.0152572,
      "daily": 1.91
    },
    {
      "symbol": "XPO",
      "weight": 0.0148174,
      "daily": 1.94
    },
    {
      "symbol": "UTHR",
      "weight": 0.0141344,
      "daily": 4.29
    },
    {
      "symbol": "FN",
      "weight": 0.014069701,
      "daily": 2.84
    },
    {
      "symbol": "MTZ",
      "weight": 0.0138885,
      "daily": -0.97
    },
    {
      "symbol": "NVT",
      "weight": 0.013249201,
      "daily": 1.82
    },
    {
      "symbol": "TWLO",
      "weight": 0.0128981,
      "daily": -2.14
    },
    {
      "symbol": "P",
      "weight": 0.0128774,
      "daily": -0.27
    }
  ]
}