{
  "symbol": "IVV",
  "holdings": [
    {
      "symbol": "NVDA",
      "weight": 0.0750593,
      "daily": -1.56
    },
    {
      "symbol": "AAPL",
      "weight": 0.0658228,
      "daily": -1.3
    },
    {
      "symbol": "MSFT",
      "weight": 0.0429165,
      "daily": -2.24
    },
    {
      "symbol": "AMZN",
      "weight": 0.036135003,
      "daily": -4.57
    },
    {
      "symbol": "GOOGL",
      "weight": 0.0324549,
      "daily": -7.13
    },
    {
      "symbol": "AVGO",
      "weight": 0.0277005,
      "daily": -1.09
    },
    {
      "symbol": "GOOG",
      "weight": 0.0258645,
      "daily": -6.89
    },
    {
      "symbol": "MU",
      "weight": 0.020162798,
      "daily": 3.2
    },
    {
      "symbol": "META",
      "weight": 0.0191593,
      "daily": -3.36
    },
    {
      "symbol": "TSLA",
      "weight": 0.0183393,
      "daily": -14.52
    }
  ]
}