{
  "symbol": "IWM",
  "holdings": [
    {
      "symbol": "BE",
      "weight": 0.0100675,
      "daily": -1.77
    },
    {
      "symbol": "CDE",
      "weight": 0.0064812,
      "daily": -0.81
    },
    {
      "symbol": "FN",
      "weight": 0.0064064995,
      "daily": -1.92
    },
    {
      "symbol": "NXT",
      "weight": 0.0059796,
      "daily": -2.99
    },
    {
      "symbol": "SATS",
      "weight": 0.005395,
      "daily": 0.84
    },
    {
      "symbol": "CRDO",
      "weight": 0.0051496,
      "daily": -5.6
    },
    {
      "symbol": "KTOS",
      "weight": 0.0043353997,
      "daily": -0.33
    },
    {
      "symbol": "AEIS",
      "weight": 0.0041381,
      "daily": -0.56
    },
    {
      "symbol": "STRL",
      "weight": 0.004132,
      "daily": -3.28
    },
    {
      "symbol": "HL",
      "weight": 0.004025,
      "daily": -0.05
    }
  ]
}