{
  "symbol": "MCHI",
  "holdings": [
    {
      "symbol": "0700.HK",
      "weight": 0.1497281,
      "daily": -0.99
    },
    {
      "symbol": "9988.HK",
      "weight": 0.111174494,
      "daily": -3.65
    },
    {
      "symbol": "00939",
      "weight": 0.0347611
    },
    {
      "symbol": "1810.HK",
      "weight": 0.0272159,
      "daily": -0.8
    },
    {
      "symbol": "PDD",
      "weight": 0.0260685,
      "daily": 4.61
    },
    {
      "symbol": "02318",
      "weight": 0.0206146
    },
    {
      "symbol": "01398",
      "weight": 0.019004
    },
    {
      "symbol": "3690.HK",
      "weight": 0.0182979,
      "daily": -2.72
    },
    {
      "symbol": "01211",
      "weight": 0.015838701
    },
    {
      "symbol": "03988",
      "weight": 0.01492
    }
  ]
}