{
  "symbol": "OIH",
  "holdings": [
    {
      "symbol": "SLB",
      "weight": 0.19656111,
      "daily": 5.52
    },
    {
      "symbol": "BKR",
      "weight": 0.1284846,
      "daily": 5.62
    },
    {
      "symbol": "HAL",
      "weight": 0.0716464,
      "daily": 1.96
    },
    {
      "symbol": "FTI",
      "weight": 0.0555012,
      "daily": 1.67
    },
    {
      "symbol": "RIG",
      "weight": 0.051835798,
      "daily": 3.36
    },
    {
      "symbol": "TS",
      "weight": 0.051009104,
      "daily": 1.59
    },
    {
      "symbol": "NE",
      "weight": 0.049529802
    },
    {
      "symbol": "WFRD",
      "weight": 0.0446136,
      "daily": 1.19
    },
    {
      "symbol": "VAL",
      "weight": 0.0421836,
      "daily": 3.39
    },
    {
      "symbol": "NOV",
      "weight": 0.0421335
    }
  ]
}