{
  "symbol": "PAVE",
  "holdings": [
    {
      "symbol": "PWR",
      "weight": 0.035712,
      "daily": 1.01
    },
    {
      "symbol": "CSX",
      "weight": 0.0349463,
      "daily": 0.83
    },
    {
      "symbol": "SRE",
      "weight": 0.0345189,
      "daily": 0.88
    },
    {
      "symbol": "DE",
      "weight": 0.032867998,
      "daily": 1.42
    },
    {
      "symbol": "ETN",
      "weight": 0.0326491,
      "daily": 3.85
    },
    {
      "symbol": "TT",
      "weight": 0.0325471,
      "daily": 2.37
    },
    {
      "symbol": "HWM",
      "weight": 0.0322798,
      "daily": 1.62
    },
    {
      "symbol": "UNP",
      "weight": 0.0319372,
      "daily": 0.82
    },
    {
      "symbol": "FAST",
      "weight": 0.0315662,
      "daily": 1.91
    },
    {
      "symbol": "NSC",
      "weight": 0.030255599,
      "daily": 0.41
    }
  ]
}