{
  "symbol": "REMX",
  "holdings": [
    {
      "symbol": "ALB",
      "weight": 0.0942344,
      "daily": 5.95
    },
    {
      "symbol": "LYC.AX",
      "weight": 0.0805993,
      "daily": -0.77
    },
    {
      "symbol": "PLS.AX",
      "weight": 0.0745532,
      "daily": 2.77
    },
    {
      "symbol": "600111.SS",
      "weight": 0.0692246,
      "daily": -0.87
    },
    {
      "symbol": "01772",
      "weight": 0.060250804
    },
    {
      "symbol": "SQM",
      "weight": 0.0580415,
      "daily": 2.82
    },
    {
      "symbol": "LTR.AX",
      "weight": 0.052051403,
      "daily": 1.79
    },
    {
      "symbol": "600549.SS",
      "weight": 0.049896304,
      "daily": -8.08
    },
    {
      "symbol": "MP",
      "weight": 0.0490679,
      "daily": 6.9
    },
    {
      "symbol": "600392.SS",
      "weight": 0.0402496,
      "daily": -2.8
    }
  ]
}