{
  "symbol": "RSP",
  "holdings": [
    {
      "symbol": "APA",
      "weight": 0.0026205,
      "daily": 0.57
    },
    {
      "symbol": "DOW",
      "weight": 0.002467,
      "daily": -3.16
    },
    {
      "symbol": "LYB",
      "weight": 0.0024343,
      "daily": -2.63
    },
    {
      "symbol": "OXY",
      "weight": 0.0023806,
      "daily": -2.07
    },
    {
      "symbol": "CIEN",
      "weight": 0.0023258,
      "daily": -1.34
    },
    {
      "symbol": "COP",
      "weight": 0.0022958,
      "daily": -1.4
    },
    {
      "symbol": "DAL",
      "weight": 0.0022882998,
      "daily": -0.37
    },
    {
      "symbol": "CTRA",
      "weight": 0.0022819,
      "daily": 0.06
    },
    {
      "symbol": "FANG",
      "weight": 0.0022793,
      "daily": -0.09
    },
    {
      "symbol": "XOM",
      "weight": 0.0022787,
      "daily": -0.76
    }
  ]
}