{
  "symbol": "RSPC",
  "holdings": [
    {
      "symbol": "VZ",
      "weight": 0.0573443,
      "daily": 1.2
    },
    {
      "symbol": "CMCSA",
      "weight": 0.054268,
      "daily": -0.03
    },
    {
      "symbol": "LYV",
      "weight": 0.0533288,
      "daily": 2.0
    },
    {
      "symbol": "T",
      "weight": 0.0524317,
      "daily": 1.59
    },
    {
      "symbol": "TKO",
      "weight": 0.0519142,
      "daily": 3.13
    },
    {
      "symbol": "TMUS",
      "weight": 0.050745,
      "daily": 0.14
    },
    {
      "symbol": "SATS",
      "weight": 0.0507178,
      "daily": -0.32
    },
    {
      "symbol": "OMC",
      "weight": 0.0503552,
      "daily": 0.77
    },
    {
      "symbol": "CHTR",
      "weight": 0.050241698,
      "daily": 1.69
    },
    {
      "symbol": "NFLX",
      "weight": 0.047386497,
      "daily": 1.7
    }
  ]
}