{
  "symbol": "URA",
  "holdings": [
    {
      "symbol": "CCO.TO",
      "weight": 0.2281663,
      "daily": -4.28
    },
    {
      "symbol": "NXE.TO",
      "weight": 0.0652624,
      "daily": -2.75
    },
    {
      "symbol": "OKLO",
      "weight": 0.064913504,
      "daily": -1.32
    },
    {
      "symbol": "UEC",
      "weight": 0.0609785,
      "daily": -8.96
    },
    {
      "symbol": "KAP",
      "weight": 0.045928
    },
    {
      "symbol": "EFR.TO",
      "weight": 0.0429466,
      "daily": -6.29
    },
    {
      "symbol": "PDN.AX",
      "weight": 0.0363628,
      "daily": -5.1
    },
    {
      "symbol": "000720.KS",
      "weight": 0.0326145,
      "daily": -5.73
    },
    {
      "symbol": "DML.TO",
      "weight": 0.0320063,
      "daily": -4.97
    }
  ]
}