{
  "symbol": "UTES",
  "holdings": [
    {
      "symbol": "TLN",
      "weight": 0.1160028,
      "daily": 0.49
    },
    {
      "symbol": "VST",
      "weight": 0.1002341,
      "daily": 1.34
    },
    {
      "symbol": "CEG",
      "weight": 0.0990368,
      "daily": 0.25
    },
    {
      "symbol": "XEL",
      "weight": 0.0683102,
      "daily": 0.72
    },
    {
      "symbol": "CNP",
      "weight": 0.065472595,
      "daily": 1.26
    },
    {
      "symbol": "ETR",
      "weight": 0.051090397,
      "daily": 0.8
    },
    {
      "symbol": "AEP",
      "weight": 0.0508946,
      "daily": 1.39
    },
    {
      "symbol": "LNT",
      "weight": 0.0508703,
      "daily": 0.54
    },
    {
      "symbol": "IDA",
      "weight": 0.046231598,
      "daily": 0.42
    },
    {
      "symbol": "SRE",
      "weight": 0.0454186,
      "daily": 0.42
    }
  ]
}