{
  "symbol": "WCLD",
  "holdings": [
    {
      "symbol": "HUBS",
      "weight": 0.0177364,
      "daily": -1.34
    },
    {
      "symbol": "FIG",
      "weight": 0.017604899,
      "daily": -2.02
    },
    {
      "symbol": "BRZE",
      "weight": 0.0172249,
      "daily": -4.58
    },
    {
      "symbol": "PAYC",
      "weight": 0.0171928,
      "daily": 0.54
    },
    {
      "symbol": "TTAN",
      "weight": 0.0169769,
      "daily": -1.12
    },
    {
      "symbol": "IOT",
      "weight": 0.0168172,
      "daily": -1.57
    },
    {
      "symbol": "PD",
      "weight": 0.0167302,
      "daily": 0.29
    },
    {
      "symbol": "TWLO",
      "weight": 0.0166918,
      "daily": -2.54
    },
    {
      "symbol": "FROG",
      "weight": 0.0166487,
      "daily": -2.74
    },
    {
      "symbol": "FSLY",
      "weight": 0.016530499,
      "daily": -4.73
    }
  ]
}