{
  "symbol": "WCLD",
  "holdings": [
    {
      "symbol": "HUBS",
      "weight": 0.0177364,
      "daily": 0.57
    },
    {
      "symbol": "FIG",
      "weight": 0.017604899,
      "daily": -3.96
    },
    {
      "symbol": "BRZE",
      "weight": 0.0172249,
      "daily": -0.49
    },
    {
      "symbol": "PAYC",
      "weight": 0.0171928,
      "daily": 0.19
    },
    {
      "symbol": "TTAN",
      "weight": 0.0169769,
      "daily": -0.02
    },
    {
      "symbol": "IOT",
      "weight": 0.0168172,
      "daily": -0.3
    },
    {
      "symbol": "PD",
      "weight": 0.0167302,
      "daily": -3.96
    },
    {
      "symbol": "TWLO",
      "weight": 0.0166918,
      "daily": -0.19
    },
    {
      "symbol": "FROG",
      "weight": 0.0166487,
      "daily": -1.92
    },
    {
      "symbol": "FSLY",
      "weight": 0.016530499,
      "daily": -14.03
    }
  ]
}