{
  "symbol": "XBI",
  "holdings": [
    {
      "symbol": "APLS",
      "weight": 0.0186512,
      "daily": 0.1
    },
    {
      "symbol": "RVMD",
      "weight": 0.0164747,
      "daily": 1.09
    },
    {
      "symbol": "TVTX",
      "weight": 0.016204601,
      "daily": -1.54
    },
    {
      "symbol": "ARWR",
      "weight": 0.014397699,
      "daily": 1.67
    },
    {
      "symbol": "TWST",
      "weight": 0.0141993,
      "daily": -0.46
    },
    {
      "symbol": "SMMT",
      "weight": 0.0140325,
      "daily": 1.55
    },
    {
      "symbol": "ALKS",
      "weight": 0.0138196,
      "daily": 7.95
    },
    {
      "symbol": "TGTX",
      "weight": 0.013710001,
      "daily": -1.39
    },
    {
      "symbol": "MDGL",
      "weight": 0.013647701,
      "daily": 2.66
    },
    {
      "symbol": "BEAM",
      "weight": 0.0132399,
      "daily": -0.54
    }
  ]
}