{
  "symbol": "XHE",
  "holdings": [
    {
      "symbol": "TFX",
      "weight": 0.0186242,
      "daily": -1.54
    },
    {
      "symbol": "STAA",
      "weight": 0.018426599,
      "daily": 0.37
    },
    {
      "symbol": "BFLY",
      "weight": 0.0184038,
      "daily": -10.19
    },
    {
      "symbol": "MDLN",
      "weight": 0.0182678,
      "daily": -1.25
    },
    {
      "symbol": "GKOS",
      "weight": 0.0182149,
      "daily": -3.12
    },
    {
      "symbol": "ITGR",
      "weight": 0.0179163,
      "daily": -0.1
    },
    {
      "symbol": "AXGN",
      "weight": 0.0178541,
      "daily": -1.5
    },
    {
      "symbol": "LIVN",
      "weight": 0.017764699,
      "daily": -3.16
    },
    {
      "symbol": "MASI",
      "weight": 0.0176369,
      "daily": -0.15
    },
    {
      "symbol": "LMAT",
      "weight": 0.0175349,
      "daily": -0.46
    }
  ]
}