{
  "symbol": "XHE",
  "holdings": [
    {
      "symbol": "NEOG",
      "weight": 0.0284345
    },
    {
      "symbol": "NVST",
      "weight": 0.0233594,
      "daily": 0.16
    },
    {
      "symbol": "LMAT",
      "weight": 0.0228533,
      "daily": -1.67
    },
    {
      "symbol": "XRAY",
      "weight": 0.0222701,
      "daily": -2.85
    },
    {
      "symbol": "MASI",
      "weight": 0.022172598,
      "daily": 1.49
    },
    {
      "symbol": "LNTH",
      "weight": 0.0217677,
      "daily": -2.8
    },
    {
      "symbol": "ITGR",
      "weight": 0.0212915,
      "daily": -0.4
    },
    {
      "symbol": "TNDM",
      "weight": 0.0208456,
      "daily": 3.27
    },
    {
      "symbol": "CNMD",
      "weight": 0.020824201,
      "daily": 0.25
    },
    {
      "symbol": "ALGN",
      "weight": 0.0204136,
      "daily": 2.23
    }
  ]
}