{
  "symbol": "XTN",
  "holdings": [
    {
      "symbol": "CAR",
      "weight": 0.0362996,
      "daily": 0.96
    },
    {
      "symbol": "RXO",
      "weight": 0.0289675,
      "daily": 0.31
    },
    {
      "symbol": "DAL",
      "weight": 0.0283088,
      "daily": -0.01
    },
    {
      "symbol": "LSTR",
      "weight": 0.027152099,
      "daily": -0.85
    },
    {
      "symbol": "ARCB",
      "weight": 0.02695,
      "daily": -0.68
    },
    {
      "symbol": "MATX",
      "weight": 0.0268183,
      "daily": -0.48
    },
    {
      "symbol": "R",
      "weight": 0.0264975,
      "daily": -1.38
    },
    {
      "symbol": "KEX",
      "weight": 0.026491301,
      "daily": -0.85
    },
    {
      "symbol": "SNDR",
      "weight": 0.026405102,
      "daily": 0.68
    },
    {
      "symbol": "ODFL",
      "weight": 0.0260659,
      "daily": -0.55
    }
  ]
}