{"built_at":"2026-07-21T22:16:00.978689+00:00","categories":{"Fed Path":[{"id":"177c7b196224","question":"Fed rate hike in 2026?","yes_prob":60.5,"probs":{"Yes":60.5,"No":39.5},"volume24hr":79659,"volume":4333429,"liquidity":109455,"end_date":"2026-12-09","outcomes":["Yes","No"],"is_binary":true,"prob_5d":null,"delta_5d":null},{"id":"5ca0db6747c2","question":"Will the Fed increase interest rates by 25 bps after the September 2026 meeting?","yes_prob":48.5,"probs":{"Yes":48.5,"No":51.5},"volume24hr":50579,"volume":967837,"liquidity":114363,"end_date":"2026-09-16","outcomes":["Yes","No"],"is_binary":true,"prob_5d":32.5,"delta_5d":16.0},{"id":"e3e2ca29b53e","question":"Will the Fed decide differently in the next three decisions (Jul\u2013Sep\u2013Oct)?","yes_prob":59.0,"probs":{"Yes":59.0,"No":41.0},"volume24hr":14493,"volume":193480,"liquidity":19990,"end_date":"2026-10-28","outcomes":["Yes","No"],"is_binary":true,"prob_5d":null,"delta_5d":null},{"id":"a8af45b838dd","question":"Fed Rate Hike by July 2026 Meeting?","yes_prob":17.6,"probs":{"Yes":17.6,"No":82.3},"volume24hr":13459,"volume":546064,"liquidity":65505,"end_date":"2026-12-09","outcomes":["Yes","No"],"is_binary":true,"prob_5d":null,"delta_5d":null}],"Markets & Crypto":[{"id":"0bcc312aa020","question":"Will Ethereum dip to $1,250 by December 31, 2026?","yes_prob":22.5,"probs":{"Yes":22.5,"No":77.5},"volume24hr":187903,"volume":355458,"liquidity":339412,"end_date":"2027-01-01","outcomes":["Yes","No"],"is_binary":true,"prob_5d":null,"delta_5d":null},{"id":"2b4dfe6f0fab","question":"Will Bitcoin dip to $50,000 by December 31, 2026?","yes_prob":31.5,"probs":{"Yes":31.5,"No":68.5},"volume24hr":49079,"volume":2283021,"liquidity":146940,"end_date":"2027-01-01","outcomes":["Yes","No"],"is_binary":true,"prob_5d":null,"delta_5d":null},{"id":"c6c7faa9b93e","question":"Will Bitcoin dip to $55,000 by December 31, 2026?","yes_prob":45.5,"probs":{"Yes":45.5,"No":54.5},"volume24hr":48985,"volume":4604742,"liquidity":147785,"end_date":"2027-01-01","outcomes":["Yes","No"],"is_binary":true,"prob_5d":null,"delta_5d":null},{"id":"fbc01e9157aa","question":"Will Ethereum dip to $1,500 by December 31, 2026?","yes_prob":43.6,"probs":{"Yes":43.6,"No":56.4},"volume24hr":30266,"volume":1511240,"liquidity":193030,"end_date":"2027-01-01","outcomes":["Yes","No"],"is_binary":true,"prob_5d":46.5,"delta_5d":-2.9},{"id":"ecd81f3b42c4","question":"Will Crude Oil reach a new all-time high by December 31?","yes_prob":16.5,"probs":{"Yes":16.5,"No":83.5},"volume24hr":19851,"volume":498564,"liquidity":32930,"end_date":"2026-12-31","outcomes":["Yes","No"],"is_binary":true,"prob_5d":null,"delta_5d":null}],"Commodities":[],"Geopolitics":[{"id":"399b6545e516","question":"Will Mojtaba Khamenei be head of state in Iran end of 2026?","yes_prob":73.0,"probs":{"Yes":73.0,"No":27.1},"volume24hr":286313,"volume":4441459,"liquidity":59600,"end_date":"2026-12-31","outcomes":["Yes","No"],"is_binary":true,"prob_5d":78.8,"delta_5d":-5.8},{"id":"020e6dca2bbd","question":"Will the U.S. invade Iran before 2027?","yes_prob":28.5,"probs":{"Yes":28.5,"No":71.5},"volume24hr":240085,"volume":45955915,"liquidity":720231,"end_date":"2026-12-31","outcomes":["Yes","No"],"is_binary":true,"prob_5d":23.5,"delta_5d":5.0},{"id":"beb72673573a","question":"Will the Iranian regime fall before 2027?","yes_prob":10.5,"probs":{"Yes":10.5,"No":89.5},"volume24hr":175362,"volume":22787088,"liquidity":619645,"end_date":"2026-12-31","outcomes":["Yes","No"],"is_binary":true,"prob_5d":null,"delta_5d":null},{"id":"91de174951f4","question":"Strait of Hormuz traffic returns to normal by August 31?","yes_prob":13.5,"probs":{"Yes":13.5,"No":86.5},"volume24hr":139876,"volume":1499345,"liquidity":252403,"end_date":"2026-08-31","outcomes":["Yes","No"],"is_binary":true,"prob_5d":null,"delta_5d":null},{"id":"88a36ba19c1c","question":"Will Ukraine recapture Crimean territory by December 31, 2026?","yes_prob":8.5,"probs":{"Yes":8.5,"No":91.5},"volume24hr":89974,"volume":2394475,"liquidity":319325,"end_date":"2026-12-31","outcomes":["Yes","No"],"is_binary":true,"prob_5d":null,"delta_5d":null}]}}