{"built_at":"2026-04-30T23:06:18.976640+00:00","categories":{"Fed / Rates":[{"id":"d7ac72f08793","question":"Will the Fed increase interest rates by 50+ bps after the June 2026 meeting?","yes_prob":0.4,"probs":{"Yes":0.4,"No":99.7},"volume24hr":1802114,"volume":5141539,"liquidity":360754,"end_date":"2026-06-17","outcomes":["Yes","No"],"is_binary":true,"prob_5d":0.4,"delta_5d":0.0},{"id":"10d9da008365","question":"Will the Fed decrease interest rates by 25 bps after the June 2026 meeting?","yes_prob":3.5,"probs":{"Yes":3.5,"No":96.5},"volume24hr":395776,"volume":2404327,"liquidity":181891,"end_date":"2026-06-17","outcomes":["Yes","No"],"is_binary":true,"prob_5d":null,"delta_5d":null},{"id":"00818bed8733","question":"Will Judy Shelton be confirmed as Fed Chair?","yes_prob":0.8,"probs":{"Yes":0.8,"No":99.2},"volume24hr":330138,"volume":17935027,"liquidity":85161,"end_date":"2026-10-31","outcomes":["Yes","No"],"is_binary":true,"prob_5d":0.9,"delta_5d":-0.1},{"id":"d703c8872103","question":"Kevin Warsh confirmed as Fed Chair by May 1?","yes_prob":0.4,"probs":{"Yes":0.4,"No":99.6},"volume24hr":237334,"volume":891122,"liquidity":6909,"end_date":"2026-05-15","outcomes":["Yes","No"],"is_binary":true,"prob_5d":null,"delta_5d":null},{"id":"759898e4f13e","question":"Will 9 Fed rate cuts happen in 2026?","yes_prob":0.2,"probs":{"Yes":0.2,"No":99.8},"volume24hr":112233,"volume":1662412,"liquidity":128018,"end_date":"2026-12-31","outcomes":["Yes","No"],"is_binary":true,"prob_5d":null,"delta_5d":null},{"id":"440dc274d562","question":"Will Kevin Warsh be confirmed as Fed Chair?","yes_prob":99.2,"probs":{"Yes":99.2,"No":0.8},"volume24hr":102073,"volume":12357565,"liquidity":84205,"end_date":"2026-10-31","outcomes":["Yes","No"],"is_binary":true,"prob_5d":98.5,"delta_5d":0.7},{"id":"099e06f9d837","question":"Will 11 Fed rate cuts happen in 2026?","yes_prob":0.2,"probs":{"Yes":0.2,"No":99.8},"volume24hr":99905,"volume":2600506,"liquidity":150305,"end_date":"2026-12-31","outcomes":["Yes","No"],"is_binary":true,"prob_5d":null,"delta_5d":null},{"id":"ade99fc28bc8","question":"Will there be no change in Fed interest rates after the July 2026 meeting?","yes_prob":87.5,"probs":{"Yes":87.5,"No":12.5},"volume24hr":70587,"volume":636365,"liquidity":240656,"end_date":"2026-07-29","outcomes":["Yes","No"],"is_binary":true,"prob_5d":null,"delta_5d":null}],"Macro":[],"Markets":[{"id":"da8f2ee7ad30","question":"Will Bitcoin hit $150k by June 30, 2026?","yes_prob":1.4,"probs":{"Yes":1.4,"No":98.7},"volume24hr":5821653,"volume":15734008,"liquidity":19823,"end_date":"2026-07-01","outcomes":["Yes","No"],"is_binary":true,"prob_5d":1.4,"delta_5d":0.0},{"id":"2e270ccac6af","question":"Will Bitcoin dip to $65,000 in April?","yes_prob":0.1,"probs":{"Yes":0.1,"No":99.9},"volume24hr":504113,"volume":7338340,"liquidity":106985,"end_date":"2026-05-01","outcomes":["Yes","No"],"is_binary":true,"prob_5d":3.0,"delta_5d":-2.9}],"Geopolitical":[{"id":"1eba3c8c0b4e","question":"Trump out as President before 2027?","yes_prob":13.5,"probs":{"Yes":13.5,"No":86.5},"volume24hr":833157,"volume":8449760,"liquidity":822373,"end_date":"2026-12-31","outcomes":["Yes","No"],"is_binary":true,"prob_5d":null,"delta_5d":null},{"id":"daac236257cb","question":"Russia x Ukraine ceasefire by May 31, 2026?","yes_prob":8.3,"probs":{"Yes":8.3,"No":91.7},"volume24hr":410017,"volume":1887800,"liquidity":89195,"end_date":"2026-05-31","outcomes":["Yes","No"],"is_binary":true,"prob_5d":null,"delta_5d":null},{"id":"66db07068e8a","question":"Will WTI Crude Oil (WTI) hit (HIGH) $150 in May?","yes_prob":8.5,"probs":{"Yes":8.5,"No":91.5},"volume24hr":404914,"volume":451313,"liquidity":78476,"end_date":"2026-06-01","outcomes":["Yes","No"],"is_binary":true,"prob_5d":null,"delta_5d":null},{"id":"c671cb2ae6fb","question":"Will Donald Trump Jr. win the 2028 US Presidential Election?","yes_prob":0.9,"probs":{"Yes":0.9,"No":99.2},"volume24hr":362832,"volume":11436436,"liquidity":218757,"end_date":"2028-11-07","outcomes":["Yes","No"],"is_binary":true,"prob_5d":null,"delta_5d":null},{"id":"04c15e7aa086","question":"Will China invade Taiwan by end of 2026?","yes_prob":7.4,"probs":{"Yes":7.4,"No":92.5},"volume24hr":335460,"volume":23356221,"liquidity":979681,"end_date":"2026-12-31","outcomes":["Yes","No"],"is_binary":true,"prob_5d":7.4,"delta_5d":0.0},{"id":"235a10c338fe","question":"Will WTI Crude Oil (WTI) hit (HIGH) $90 in May?","yes_prob":99.5,"probs":{"Yes":99.5,"No":0.5},"volume24hr":222794,"volume":270060,"liquidity":44931,"end_date":"2026-06-01","outcomes":["Yes","No"],"is_binary":true,"prob_5d":null,"delta_5d":null},{"id":"9af7704199bc","question":"Russia x Ukraine ceasefire by June 30, 2026?","yes_prob":13.5,"probs":{"Yes":13.5,"No":86.5},"volume24hr":192491,"volume":7774731,"liquidity":205262,"end_date":"2026-06-30","outcomes":["Yes","No"],"is_binary":true,"prob_5d":null,"delta_5d":null},{"id":"ac1be14ee29c","question":"Will China invade Taiwan by June 30, 2026?","yes_prob":2.1,"probs":{"Yes":2.1,"No":97.9},"volume24hr":144111,"volume":7596545,"liquidity":98579,"end_date":"2026-06-30","outcomes":["Yes","No"],"is_binary":true,"prob_5d":null,"delta_5d":null}]}}